<?xml version="1.0" encoding="UTF-8" standalone="no"?>
<configuration>
	<feature automatic="selected" name="BookManagementTask2"/>
	<feature automatic="selected" name="GUI"/>
	<feature automatic="selected" name="LocalManagement"/>
	<feature automatic="selected" name="Attribute"/>
	<feature automatic="selected" manual="selected" name="Name"/>
	<feature automatic="selected" manual="selected" name="Price"/>
	<feature automatic="selected" manual="selected" name="Algorithm"/>
	<feature manual="selected" name="PriceSort"/>
</configuration>
